langchain_fireworks/__init__.py
langchain_fireworks/chat_models.py
langchain_fireworks/embeddings.py
langchain_fireworks/llms.py
langchain_fireworks/py.typed
langchain_fireworks/version.py
gigachain_fireworks-0.1.7.dist-info/LICENSE
gigachain_fireworks-0.1.7.dist-info/METADATA
gigachain_fireworks-0.1.7.dist-info/WHEEL
gigachain_fireworks-0.1.7.dist-info/RECORD
