Metadata-Version: 2.1
Name: gigachain-fireworks
Version: 0.1.7
Summary: An integration package connecting Fireworks and GigaChain
Home-page: https://github.com/ai-forever/gigachain
License: MIT
Requires-Python: >=3.8.1,<4.0
Classifier: License :: OSI Approved :: MIT License
Classifier: Programming Language :: Python :: 3
Classifier: Programming Language :: Python :: 3.9
Classifier: Programming Language :: Python :: 3.10
Classifier: Programming Language :: Python :: 3.11
Classifier: Programming Language :: Python :: 3.12
Requires-Dist: aiohttp (>=3.9.1,<4.0.0)
Requires-Dist: fireworks-ai (>=0.13.0)
Requires-Dist: gigachain-core (>=0.2.26,<0.3.0)
Requires-Dist: openai (>=1.10.0,<2.0.0)
Requires-Dist: requests (>=2,<3)
Project-URL: Repository, https://github.com/ai-forever/gigachain
Project-URL: Release Notes, https://github.com/ai-forever/gigachain/releases?q=tag%3A%22gigachain-fireworks%3D%3D0%22&expanded=true
Project-URL: Source Code, https://github.com/ai-forever/gigachain/tree/master/libs/partners/fireworks
